Metadata-Version: 1.0
Name: heroqsx-distributions
Version: 0.1
Summary: Gaussian and Binomial distributions
Home-page: UNKNOWN
Author: Gebing Qiu
Author-email: 1017809810@qq.com
License: UNKNOWN
Platform: UNKNOWN
